llm_chain/__init__.py
llm_chain/base.py
llm_chain/exceptions.py
llm_chain/indexes.py
llm_chain/memory.py
llm_chain/models.py
llm_chain/prompt_templates.py
llm_chain/resources.py
llm_chain/tools.py
llm_chain/utilities.py
tests/__init__.py
tests/conftest.py
tests/test_chains.py
tests/test_indexes.py
tests/test_link.py
tests/test_memory.py
tests/test_models.py
tests/test_prompt_templates.py
tests/test_records.py
tests/test_session.py
tests/test_tools.py
tests/test_utilities.py
llm_chain-0.0.19.dist-info/LICENSE
llm_chain-0.0.19.dist-info/METADATA
llm_chain-0.0.19.dist-info/WHEEL
llm_chain-0.0.19.dist-info/top_level.txt
llm_chain-0.0.19.dist-info/RECORD
