Metadata-Version: 2.1
Name: llm-chain
Version: 0.0.19
Summary: Simple and extensible LLM Chaining
Home-page: https://github.com/shane-kercheval/llm-chain
Author: Shane Kercheval
Author-email: shane.kercheval@gmail.com
Project-URL: Bug Tracker, https://github.com/shane-kercheval/llm-chain/issues
Classifier: Programming Language :: Python :: 3
Classifier: License :: OSI Approved :: MIT License
Classifier: Operating System :: OS Independent
Requires-Python: >=3.10
License-File: LICENSE
Requires-Dist: pydantic
Requires-Dist: tenacity
Requires-Dist: tiktoken
